{"sections":{"main":{"type":"main-404","disabled":true,"settings":{}},"rich_text_xK9JkF":{"type":"rich-text","blocks":{"text_iBK6K7":{"type":"text","settings":{"text":"<p>RUBBISH!<\/p>"}},"heading_4jQztF":{"type":"heading","settings":{"heading":"It appears whatever you were looking for has wandered off in search of a good beer.","heading_size":"h2"}},"text_CLhWhT":{"type":"text","settings":{"text":"<p>We apologize for the inconvenience. <\/p><p>Feel free to visit our <a href=\"https:\/\/berobrewing.com\/collections\/frontpage\"><span style=\"text-decoration:underline\">home page<\/span><\/a>, search again in the menu above, or <a href=\"\/collections\/all\" title=\"All products\"><span style=\"text-decoration:underline\">explore our collection.<\/span><\/a><\/p>"}},"button_cC6twm":{"type":"button","settings":{"button_label":"Head Home","button_link":"\/","button_style_secondary":false,"button_label_2":"EXPLORE ALL BEERS","button_link_2":"shopify:\/\/collections\/our-beers","button_style_secondary_2":true}}},"block_order":["text_iBK6K7","heading_4jQztF","text_CLhWhT","button_cC6twm"],"custom_css":["@media only screen and (min-width: 768px) {.rich-text__buttons {gap: 3rem; max-width: 100%; }}","@media only screen and (max-width: 768px) {.rich-text__wrapper {padding: 0; } .button--primary {max-width: 80%; } .rich-text__buttons {gap: 2rem; } .button {padding: 24px 10px; }}","h2 {font-family: \"ABCWhyte\", Assistant, sans-serif;}",".rich-text__text a {text-decoration: underline;}"],"settings":{"desktop_content_position":"center","content_alignment":"center","color_scheme":"","full_width":true,"padding_top":100,"padding_bottom":100}},"pbj_image_banner_awBwag":{"type":"pbj-image-banner","settings":{"add_shrink_effect":false,"customer_status":"all","color_scheme":"","desktop_image":"shopify:\/\/shop_images\/Overlay_A.jpg","overlay_opacity":50,"hide_bg_color":true,"transparent_header":false,"title":"","space_negative_top":0,"space_negative_top_mobile":0,"full_width":false,"padding_top":40,"padding_bottom":52}}},"order":["main","rich_text_xK9JkF","pbj_image_banner_awBwag"]}